big_python_library/__init__.py
big_python_library/main.py
big_python_library-0.1.1.dist-info/METADATA
big_python_library-0.1.1.dist-info/WHEEL
big_python_library-0.1.1.dist-info/RECORD
