Metadata-Version: 2.4
Name: big_python_library
Version: 0.1.1
Summary: This is an internal python library
Author: =
Author-email: kevin.c-dubois@wiz.io
Requires-Python: >=3.8
Classifier: Programming Language :: Python :: 3
Classifier: Programming Language :: Python :: 3.8
Classifier: Programming Language :: Python :: 3.9
Classifier: Programming Language :: Python :: 3.10
Classifier: Programming Language :: Python :: 3.11
Classifier: Programming Language :: Python :: 3.12
Classifier: Programming Language :: Python :: 3.13
Classifier: Programming Language :: Python :: 3.14
Requires-Dist: torch (==2.2.0)
Project-URL: Repository, https://github.com/kcduboiswiz/big-python-library
